heron/__init__.py
heron/base.py
heron/category.py
heron/end_user.py
heron/error.py
heron/merchant.py
heron/providers.py
heron/transaction.py
heron/utils.py
heron_data-0.1.4.dist-info/LICENSE
heron_data-0.1.4.dist-info/METADATA
heron_data-0.1.4.dist-info/WHEEL
heron_data-0.1.4.dist-info/top_level.txt
heron_data-0.1.4.dist-info/RECORD
