Metadata-Version: 2.1
Name: heron-data
Version: 0.1.4
Summary: A client for the Heron Data API
Home-page: https://github.com/heron-data/client-python
Author: Heron Data
Author-email: help@herondata.io
License: MIT
Classifier: License :: OSI Approved :: MIT License
Classifier: Intended Audience :: Developers
Classifier: Programming Language :: Python
Classifier: Programming Language :: Python :: 3
Requires-Python: >=3.8.*
License-File: LICENSE
Requires-Dist: requests (~=2.26.0)
